validator_schema/__init__.py
validator_schema/validator_schema.py
validator_schema-0.1.0.dist-info/METADATA
validator_schema-0.1.0.dist-info/WHEEL
validator_schema-0.1.0.dist-info/RECORD
