Metadata-Version: 2.1
Name: validator-schema
Version: 0.1.0
Summary: Um validador para schema json usado em APIs Rest
Author: Marcos Felipe
Author-email: plimo263@gmail.com
Requires-Python: >=3.7,<4.0
Classifier: Programming Language :: Python :: 3
Classifier: Programming Language :: Python :: 3.7
Classifier: Programming Language :: Python :: 3.8
Classifier: Programming Language :: Python :: 3.9
Classifier: Programming Language :: Python :: 3.10
Classifier: Programming Language :: Python :: 3.11
Requires-Dist: jsonschema (>=4.17.3,<5.0.0)
